gradio_agentchatbot_5/__init__.py
gradio_agentchatbot_5/agentchatbot.py
gradio_agentchatbot_5/agentchatbot.pyi
gradio_agentchatbot_5/utils.py
gradio_agentchatbot_5/templates/component/index.js
gradio_agentchatbot_5/templates/component/style.css
gradio_agentchatbot_5/templates/component/assets/worker-lPYB70QI.js
gradio_agentchatbot_5-0.0.11.dist-info/METADATA
gradio_agentchatbot_5-0.0.11.dist-info/WHEEL
gradio_agentchatbot_5-0.0.11.dist-info/licenses/LICENSE
gradio_agentchatbot_5-0.0.11.dist-info/RECORD
