Metadata-Version: 2.4
Name: gradio_agentchatbot_5
Version: 0.0.11
Summary: Chat with agents 🤖 and see the tools they use 🛠️
Author-email: Freddy Boulton <alfonsoboulton@gmail.com>
License-Expression: Apache-2.0
License-File: LICENSE
Keywords: agents,chatbot,gradio-custom-component,gradio-template-Chatbot,streaming,tools
Classifier: Development Status :: 3 - Alpha
Classifier: Operating System :: OS Independent
Classifier: Programming Language :: Python :: 3
Classifier: Programming Language :: Python :: 3 :: Only
Classifier: Programming Language :: Python :: 3.8
Classifier: Programming Language :: Python :: 3.9
Classifier: Programming Language :: Python :: 3.10
Classifier: Programming Language :: Python :: 3.11
Classifier: Topic :: Scientific/Engineering
Classifier: Topic :: Scientific/Engineering :: Artificial Intelligence
Classifier: Topic :: Scientific/Engineering :: Visualization
Requires-Python: >=3.8
Requires-Dist: gradio<6.0,>=4.0
Provides-Extra: dev
Requires-Dist: build; extra == 'dev'
Requires-Dist: twine; extra == 'dev'
